delanalysis.py
delanalysis-0.2.3.dist-info/LICENSE
delanalysis-0.2.3.dist-info/METADATA
delanalysis-0.2.3.dist-info/WHEEL
delanalysis-0.2.3.dist-info/top_level.txt
delanalysis-0.2.3.dist-info/RECORD
