Metadata-Version: 2.1
Name: delanalysis
Version: 0.2.3
Summary: An analysis algoritm that is a companion to NGS-Barcode-Count
Home-page: https://github.com/Roco-scientist/DEL-Analysis
Author: Rory Coffey
Author-email: coffeyrt@gmail.com
License: UNKNOWN
Platform: UNKNOWN
Classifier: Programming Language :: Python :: 3
Classifier: License :: OSI Approved :: MIT License
Classifier: Operating System :: OS Independent
Requires-Python: ~=3.9
License-File: LICENSE
Requires-Dist: pandas (==1.2)
Requires-Dist: plotly (==5.3)
Requires-Dist: scipy (==1.6)
